README.rst
setup.py
sinbad/__init__.py
sinbad/cacher.py
sinbad/comm.py
sinbad/datasource.py
sinbad/describe.py
sinbad/dot_printer.py
sinbad/plugin_base.py
sinbad/plugin_csv.py
sinbad/plugin_json.py
sinbad/plugin_satori.py
sinbad/plugin_xml.py
sinbad/prefs.py
sinbad/sinbad_error.py
sinbad/util.py
sinbad/version.py
sinbad.egg-info/PKG-INFO
sinbad.egg-info/SOURCES.txt
sinbad.egg-info/dependency_links.txt
sinbad.egg-info/pbr.json
sinbad.egg-info/requires.txt
sinbad.egg-info/top_level.txt