Metadata-Version: 1.1
Name: sinbad
Version: 0.5b6
Summary: A library for uniform, easy access to online data sources in standard formats
Home-page: http://cs.berry.edu/sinbad/
Author: Nadeem Abdul Hamid
Author-email: nadeem@acm.org
License: MIT
Keywords: data access xml json csv
Platform: UNKNOWN
Classifier: Development Status :: 4 - Beta
Classifier: Intended Audience :: Education
Classifier: Topic :: Software Development :: Libraries
Classifier: License :: OSI Approved :: MIT License
Classifier: Programming Language :: Python :: 3.5
Classifier: Programming Language :: Python :: 3.6
